chrome_profile_manager/__init__.py
chrome_profile_manager/__main__.py
chrome_profile_manager/main.py
chrome_profile_manager/helpers/__init__.py
chrome_profile_manager/helpers/alias_creator.py
chrome_profile_manager/utils/__init__.py
chrome_profile_manager/utils/chrome_scanner.py
chrome_profile_manager-0.1.0.dist-info/METADATA
chrome_profile_manager-0.1.0.dist-info/WHEEL
chrome_profile_manager-0.1.0.dist-info/entry_points.txt
chrome_profile_manager-0.1.0.dist-info/top_level.txt
chrome_profile_manager-0.1.0.dist-info/RECORD
