Metadata-Version: 2.1
Name: chrome-profile-manager
Version: 0.1.0
Summary: A friendly Chrome profile manager for quick profile switching
Home-page: https://github.com/yourusername/chrome-profile-manager
Author: Your Name
Author-email: your.email@example.com
Classifier: Programming Language :: Python :: 3
Classifier: License :: OSI Approved :: MIT License
Classifier: Operating System :: POSIX :: Linux
Requires-Python: >=3.8
Requires-Dist: rich>=10.0.0
